setup.py
Cleverbox.egg-info/PKG-INFO
Cleverbox.egg-info/SOURCES.txt
Cleverbox.egg-info/dependency_links.txt
Cleverbox.egg-info/requires.txt
Cleverbox.egg-info/top_level.txt
cleverbox/__init__.py
cleverbox/scripts/__init__.py
cleverbox/scripts/admin.py
cleverbox/upgrades/__init__.py
cleverbox/upgrades/upgrades.py
scripts/cleverbox-admin
