Metadata-Version: 1.0
Name: Cleverbox
Version: 0.4.4
Summary: Script for automating multiple trac instances deployment and maintenance.
Home-page: http://www.clever-age.org/trac/wiki/cleverbox
Author: Tristan Rivoallan
Author-email: trivoallan@clever-age.com
License: GPLv3
Platform: UNKNOWN
